[
	{
		"name": "Gandi",
		"logo": "/img/lego.svg",
		"type": "bronze"
	},
	{
		"name": "IIM Digital School",
		"logo": "/img/lego.svg",
		"type": "bronze"
	},
	{
		"name": "Proton",
		"logo": "/img/lego.svg",
		"type": "bronze"
	},
	{
		"name": "LebonCoin",
		"logo": "/img/lego.svg",
		"type": "argent"
	},
	{
		"name": "Temesis",
		"logo": "/img/lego.svg",
		"type": "argent"
	},
	{
		"name": "Balsamiq",
		"logo": "/img/lego.svg",
		"type": "argent"
	},
	{
		"name": "mc2i",
		"logo": "/img/lego.svg",
		"type": "argent"
	},
	{
		"name": "MAIF",
		"logo": "/img/lego.svg",
		"type": "argent"
	},
	{
		"name": "HelloWork",
		"logo": "/img/lego.svg",
		"type": "or"
	},
	{
		"name": "o2switch",
		"logo": "/img/lego.svg",
		"type": "or"
	}
]
